README.md
setup.cfg
setup.py
tests/__init__.py
tests/test_cascade.py
tests/test_connector.py
tests/test_controls.py
tests/test_flask_server.py
tests/test_image_manager.py
tests/test_message_logging.py
tests/test_nlg_markup.py
tests/test_phrase.py
tests/test_utils.py
tests/test_managers/__init__.py
tests/test_managers/test_faq.py
tests/test_managers/test_form.py
tests/test_managers/test_fsa.py
tests/test_managers/test_turn_dm.py
tests/test_nlg/__init__.py
tests/test_nlg/test_morph.py
tests/test_nlg/test_sampling.py
tests/test_nlu/__init__.py
tests/test_nlu/test_matchers.py
tests/test_nlu/test_regex_expander.py
tests/test_vk_api/__init__.py
tests/test_vk_api/test_methods.py
tgalice/__init__.py
tgalice/criteria.py
tgalice/dialog_connector.py
tgalice.egg-info/PKG-INFO
tgalice.egg-info/SOURCES.txt
tgalice.egg-info/dependency_links.txt
tgalice.egg-info/requires.txt
tgalice.egg-info/top_level.txt
tgalice/adapters/__init__.py
tgalice/adapters/alice.py
tgalice/adapters/base.py
tgalice/adapters/facebook.py
tgalice/adapters/salut.py
tgalice/adapters/text.py
tgalice/adapters/tg.py
tgalice/adapters/vk.py
tgalice/cascade/__init__.py
tgalice/cascade/cascade.py
tgalice/cascade/turn.py
tgalice/dialog/__init__.py
tgalice/dialog/context.py
tgalice/dialog/names.py
tgalice/dialog/phrase.py
tgalice/dialog/response.py
tgalice/dialog/serialized_message.py
tgalice/dialog_manager/__init__.py
tgalice/dialog_manager/automaton.py
tgalice/dialog_manager/base.py
tgalice/dialog_manager/faq.py
tgalice/dialog_manager/form_filling.py
tgalice/dialog_manager/turning.py
tgalice/interfaces/__init__.py
tgalice/interfaces/vk.py
tgalice/interfaces/yandex/__init__.py
tgalice/interfaces/yandex/request.py
tgalice/interfaces/yandex/response.py
tgalice/nlg/__init__.py
tgalice/nlg/controls.py
tgalice/nlg/morph.py
tgalice/nlg/reply_markup.py
tgalice/nlg/sampling.py
tgalice/nlu/__init__.py
tgalice/nlu/basic_nlu.py
tgalice/nlu/matchers.py
tgalice/nlu/regex_expander.py
tgalice/nlu/regex_utils.py
tgalice/server/__init__.py
tgalice/server/flask_ngrok.py
tgalice/server/flask_server.py
tgalice/storage/__init__.py
tgalice/storage/database_utils.py
