Metadata-Version: 2.1
Name: tgalice
Version: 0.2.28
Summary: Yet another common wrapper for Alice/Salut skills and Facebook/Telegram/VK bots
Home-page: https://github.com/avidale/tgalice
Author: David Dale
Author-email: dale.david@mail.ru
License: MIT
Platform: UNKNOWN
Classifier: Development Status :: 3 - Alpha
Classifier: Programming Language :: Python :: 3
Classifier: License :: OSI Approved :: MIT License
Classifier: Operating System :: OS Independent
Provides-Extra: rumorph
Provides-Extra: server
Provides-Extra: w2v
